SemiCPack/Main.py
SemiCPack/__init__.py
SemiCPack-0.1.0.dist-info/METADATA
SemiCPack-0.1.0.dist-info/WHEEL
SemiCPack-0.1.0.dist-info/entry_points.txt
SemiCPack-0.1.0.dist-info/top_level.txt
SemiCPack-0.1.0.dist-info/RECORD
