Metadata-Version: 2.1
Name: SemiCPack
Version: 0.1.0
Summary: A Python plugin for GUI support
Home-page: UNKNOWN
License: UNKNOWN
Platform: UNKNOWN
